pdf2str/__init__.py
pdf2str/pdf_to_str.py
pdf2str/pdf_to_txt.py
pdf2str-0.0.4.dist-info/METADATA
pdf2str-0.0.4.dist-info/WHEEL
pdf2str-0.0.4.dist-info/licenses/LICENSE
pdf2str-0.0.4.dist-info/RECORD
