Metadata-Version: 2.3
Name: pdf2str
Version: 0.0.4
Summary: Package to convert PDF files to strings or .txt files.
Project-URL: Homepage, https://github.com/bdcdo/pdf2str
Project-URL: Issues, https://github.com/bdcdo/pdf2str/issues
Author-email: Bruno Oliveira <bruno.oliveira.pgsp@gmail.com>
License-File: LICENSE
Classifier: License :: OSI Approved :: MIT License
Classifier: Operating System :: OS Independent
Classifier: Programming Language :: Python :: 3
Requires-Python: >=3.8
Requires-Dist: pypdf2
